dbt_lineage_viewer/__init__.py
dbt_lineage_viewer/main.py
dbt_lineage_viewer/mermaid.py
dbt_lineage_viewer/model.py
dbt_lineage_viewer/utils.py
dbt_lineage_viewer-1.0.4.dist-info/METADATA
dbt_lineage_viewer-1.0.4.dist-info/WHEEL
dbt_lineage_viewer-1.0.4.dist-info/entry_points.txt
dbt_lineage_viewer-1.0.4.dist-info/top_level.txt
dbt_lineage_viewer-1.0.4.dist-info/RECORD
