Metadata-Version: 2.1
Name: dbt-lineage-viewer
Version: 1.0.4
Summary: A DBT lineage viewer
Home-page: https://github.com/ydai713/dbt-lineage-viewer
Author: Yang Dai
Author-email: yang.dai2020@gmail.com
Requires-Dist: click
